video_content_extractor_mcp/__init__.py
video_content_extractor_mcp/main.py
video_content_extractor_mcp-0.1.12.dist-info/METADATA
video_content_extractor_mcp-0.1.12.dist-info/WHEEL
video_content_extractor_mcp-0.1.12.dist-info/entry_points.txt
video_content_extractor_mcp-0.1.12.dist-info/RECORD
