Metadata-Version: 2.4
Name: video-content-extractor-mcp
Version: 0.1.12
Summary: MCP server for video content extraction: audio extraction, video trimming, frame extraction, and scene detection
Author-email: Your Name <your.email@example.com>
License: MIT
Keywords: audio,extraction,ffmpeg,mcp,media-processing,video
Classifier: Development Status :: 4 - Beta
Classifier: Intended Audience :: Developers
Classifier: License :: OSI Approved :: MIT License
Classifier: Programming Language :: Python :: 3
Classifier: Programming Language :: Python :: 3.12
Classifier: Topic :: Multimedia :: Sound/Audio
Classifier: Topic :: Multimedia :: Video
Classifier: Topic :: Software Development :: Libraries :: Python Modules
Requires-Python: >=3.12
Requires-Dist: ffmpeg-python>=0.2.0
Requires-Dist: mcp[cli]>=1.9.0
